toolkit/__init__.py
toolkit/_version.py
toolkit/cli.py
toolkit/logger.py
toolkit/config/__init__.py
toolkit/config/context.py
toolkit/config/fs.py
toolkit/config/python.py
toolkit/config/runtime.py
toolkit/config/serialize.py
toolkit/config/settings.py
toolkit/fs/__init__.py
toolkit/fs/dir.py
toolkit/profile/__init__.py
toolkit/profile/notify.py
toolkit/profile/perf.py
toolkit/provider/__init__.py
toolkit/provider/tidy.py
toolkit/provider/unzip.py
toolkit/provider/youdao.py
toolkit/provider/image_hosting/__init__.py
toolkit/provider/image_hosting/common.py
toolkit/provider/image_hosting/jd.py
toolkit/provider/image_hosting/sogou.py
toolkit/provider/user_agent/__init__.py
toolkit/provider/user_agent/generate.py
toolkit/render/__init__.py
toolkit/render/core.py
toolkit/render/cutter.py
toolkit/scaffold/__init__.py
toolkit/scaffold/config/__init__.py
toolkit/scaffold/config/alias.py
toolkit/scaffold/config/cli.py
toolkit/scaffold/config/git.py
toolkit/scaffold/config/hosts.py
toolkit/scaffold/config/pwsh.py
toolkit/scaffold/config/python.py
toolkit/scaffold/config/template.py
toolkit/scaffold/config/vim.py
toolkit/scaffold/mirror/__init__.py
toolkit/scaffold/mirror/cli.py
toolkit/scaffold/mirror/golang.py
toolkit/scaffold/mirror/python.py
toolkit/scaffold/project/__init__.py
toolkit/scaffold/project/cli.py
toolkit/scaffold/project/command.py
toolkit/scaffold/project/context.py
toolkit/scaffold/project/render.py
toolkit/scaffold/project/template.py
toolkit/scaffold/project/ansible/__init__.py
toolkit/scaffold/project/ansible/cli.py
toolkit/scaffold/project/ansible/context.py
toolkit/scaffold/project/cpp/__init__.py
toolkit/scaffold/project/cpp/cli.py
toolkit/scaffold/project/cpp/example.py
toolkit/scaffold/project/cpp/qt5/__init__.py
toolkit/scaffold/project/cpp/qt5/cli.py
toolkit/scaffold/project/cpp/qt5/console.py
toolkit/scaffold/project/cpp/qt5/context.py
toolkit/scaffold/project/cpp/qt5/example.py
toolkit/scaffold/project/cpp/qt6/__init__.py
toolkit_py-1.5.10.dist-info/AUTHORS.md
toolkit_py-1.5.10.dist-info/LICENSE
toolkit_py-1.5.10.dist-info/METADATA
toolkit_py-1.5.10.dist-info/WHEEL
toolkit_py-1.5.10.dist-info/entry_points.txt
toolkit_py-1.5.10.dist-info/top_level.txt
toolkit_py-1.5.10.dist-info/RECORD
