Metadata-Version: 2.1
Name: toolkit-py
Version: 1.5.10
Summary: Personal toolkit implemented by Python.
Home-page: https://github.com/fujiawei-dev/toolkit-py
Author: Rustle Karl
Author-email: fu.jiawei@outlook.com
License: MIT license
Keywords: toolkit
Classifier: Environment :: Console
Classifier: Intended Audience :: Developers
Classifier: Operating System :: OS Independent
Classifier: License :: OSI Approved :: MIT License
Classifier: Programming Language :: Python :: 3
Classifier: Programming Language :: Python :: 3.9
Classifier: Programming Language :: Python :: 3.10
Classifier: Topic :: Software Development
Requires-Python: >=3.9
License-File: LICENSE
License-File: AUTHORS.md
Requires-Dist: binaryornot (~=0.4.4)
Requires-Dist: chardet (~=4.0.0)
Requires-Dist: click (~=8.0.4)
Requires-Dist: click-aliases (~=1.0.1)
Requires-Dist: cookiecutter (~=2.1.1)
Requires-Dist: jinja2 (~=3.1.2)
Requires-Dist: lxml (~=4.9.0)
Requires-Dist: pillow (~=9.0.1)
Requires-Dist: pydantic[dotenv] (~=1.9.0)
Requires-Dist: pyperclip (~=1.8.2)
Requires-Dist: pyyaml (~=6.0)
Requires-Dist: requests (~=2.27.1)
Provides-Extra: dev
Requires-Dist: black ; extra == 'dev'
Requires-Dist: build ; extra == 'dev'
Requires-Dist: flake8 ; extra == 'dev'
Requires-Dist: pre-commit ; extra == 'dev'
Requires-Dist: pytest ; extra == 'dev'
Requires-Dist: pytest-click ; extra == 'dev'
Requires-Dist: pytest-cov ; extra == 'dev'
Requires-Dist: pytest-faker ; extra == 'dev'
Requires-Dist: versioneer ; extra == 'dev'
